pgspecial/__init__.py
pgspecial/dbcommands.py
pgspecial/iocommands.py
pgspecial/main.py
pgspecial/namedqueries.py
pgspecial/help/__init__.py
pgspecial/help/commands.py
pgspecial-2.2.0.dist-info/METADATA
pgspecial-2.2.0.dist-info/WHEEL
pgspecial-2.2.0.dist-info/entry_points.txt
pgspecial-2.2.0.dist-info/top_level.txt
pgspecial-2.2.0.dist-info/RECORD
