Metadata-Version: 2.4
Name: pgspecial
Version: 2.2.0
Summary: Meta-commands handler for Postgres Database.
Author-email: Pgcli Core Team <pgcli-dev@googlegroups.com>
License: BSD
Keywords: postgres,database,cli,meta-commands
Requires-Python: >=3.9
Requires-Dist: click>=4.1
Requires-Dist: sqlparse>=0.1.19
Requires-Dist: psycopg>=3.0.10
Provides-Extra: dev
Requires-Dist: pytest>=6.2.4; extra == "dev"
Requires-Dist: coverage; extra == "dev"
Requires-Dist: codecov>=1.5.1; extra == "dev"
Requires-Dist: pre-commit>=1.16.0; extra == "dev"
Requires-Dist: configobj>=5.0.6; extra == "dev"
Requires-Dist: ruff>=0.11.7; extra == "dev"
Requires-Dist: tox>=4.8.0; extra == "dev"
Requires-Dist: pdbpp>=0.10.3; extra == "dev"
